{
  "tags": [
    "aws",
    "sns",
    "notification"
  ],
  "api": "0.1",
  "resources": [
  ],
  "version": "0.0.3",
  "license": "Artistic-2.0",
  "description": "Description of an AWS Simple Notification Service message",
  "authors": [
    "Jonathan Stowe <jns+gh@gellyfish.co.uk>"
  ],
  "raku": "6.d",
  "support": {
    "email": "jns+gh@gellyfish.co.uk",
    "source": "https://github.com/jonathanstowe/AWS-SNS-Notification.git"
  },
  "meta-version": "2",
  "name": "AWS::SNS::Notification",
  "auth": "zef:jonathanstowe",
  "depends": [
    "Cro::HTTP::Client",
    "OpenSSL",
    "Base64",
    "URI"
  ],
  "test-depends": [
    "JSON::Fast",
    "Test::Mock"
  ],
  "build-depends": [
  ],
  "source-url": "https://github.com/jonathanstowe/AWS-SNS-Notification.git",
  "provides": {
    "AWS::SNS::Notification": "lib/AWS/SNS/Notification.rakumod"
  }
}